face_hunters/AutoEncoder.py
face_hunters/Documentation.html
face_hunters/__init__.py
face_hunters/alabaster.css
face_hunters/custom.css
face_hunters/decodeur.h5
face_hunters/detective.png
face_hunters/detective_fem.jpg
face_hunters/detective_hom.png
face_hunters/doctools.js
face_hunters/documentation_options.js
face_hunters/encodeur.h5
face_hunters/evolutionary.py
face_hunters/filter_data.py
face_hunters/gadget.jpg
face_hunters/img_female_old_straight.csv.npy
face_hunters/img_female_old_wavy.csv.npy
face_hunters/img_female_young_straight.csv.npy
face_hunters/img_female_young_wavy.csv.npy
face_hunters/img_male_old_beard.csv.npy
face_hunters/img_male_old_nobeard.csv.npy
face_hunters/img_male_young_beard.csv.npy
face_hunters/img_male_young_nobeard.csv.npy
face_hunters/index.html
face_hunters/interface.py
face_hunters/jquery.js
face_hunters/logo_insa.png
face_hunters/pygments.css
face_hunters/reposant.jpg
face_hunters/underscore.js
face_hunters-0.6.7.dist-info/LICENSE
face_hunters-0.6.7.dist-info/METADATA
face_hunters-0.6.7.dist-info/WHEEL
face_hunters-0.6.7.dist-info/top_level.txt
face_hunters-0.6.7.dist-info/RECORD
